{
  "tdt": {
    "latest_version": "4.5.1",
    "last_update_date": "19.11.2023",
    "repo_url": "https://gitlabe2.ext.net.nokia.com/tsioros/TDT_simple",
    "note": "added: Support for automatic check for online updates"
  },
  "capscli_decrypt": {
    "latest_version": "1.9.1",
    "last_update_date": "19.11.2023",
    "repo_url": "https://gitlabe2.ext.net.nokia.com/tsioros/capscli_decrypt",
    "note": ""
  },
  "perf_parser": {
    "latest_version": "1.13.1",
    "last_update_date": "19.11.2023",
    "repo_url": "https://gitlabe2.ext.net.nokia.com/CMMtools/perf_parsing_scripts",
    "note": ""
  },
  "pcmd_parser": {
    "latest_version": "0.0.4_beta",
    "last_update_date": "13.11.2023",
    "repo_url": "https://gitlabe2.ext.net.nokia.com/CMMtools/pcmd_parser",
    "note": "added: Support for automatic check for online updates"
  },
  "cmmlogcollect": {
    "latest_version": "1.7.2",
    "last_update_date": "20.12.2022",
    "repo_url": "https://gitlabe2.ext.net.nokia.com/CMMtools/cmmlogcollect",
    "note": ""
  },
  "test": {
    "latest_version": "1.7.2",
    "last_update_date": "20.12.2022",
    "repo_url": "https://test.com",
    "note": "extra note/comment that might be need to be communicated as well"
  }
}
